README
setup.py
wayround_org/pyeditor/__init__.py
wayround_org/pyeditor/add_project_dialog.py
wayround_org/pyeditor/buffer.py
wayround_org/pyeditor/buffer_clip.py
wayround_org/pyeditor/config.py
wayround_org/pyeditor/main.py
wayround_org/pyeditor/main_menu.py
wayround_org/pyeditor/main_window.py
wayround_org/pyeditor/module_commons.py
wayround_org/pyeditor/project_clip.py
wayround_org/pyeditor/project_menu.py
wayround_org/pyeditor/rename_file_dialog.py
wayround_org/pyeditor/start_main.py
wayround_org/pyeditor/modes/__init__.py
wayround_org/pyeditor/modes/c.py
wayround_org/pyeditor/modes/cpp.py
wayround_org/pyeditor/modes/cython.py
wayround_org/pyeditor/modes/cython_pxd.py
wayround_org/pyeditor/modes/dummy.py
wayround_org/pyeditor/modes/java.py
wayround_org/pyeditor/modes/javascript.py
wayround_org/pyeditor/modes/makefile.py
wayround_org/pyeditor/modes/python.py
wayround_org/pyeditor/modes/text_plain.py
wayround_org/pyeditor/modes/vala.py
wayround_org/pyeditor/modes/xml.py
wayround_org_pyeditor.egg-info/PKG-INFO
wayround_org_pyeditor.egg-info/SOURCES.txt
wayround_org_pyeditor.egg-info/dependency_links.txt
wayround_org_pyeditor.egg-info/entry_points.txt
wayround_org_pyeditor.egg-info/requires.txt
wayround_org_pyeditor.egg-info/top_level.txt