Metadata-Version: 1.1
Name: wayround-org-pyeditor
Version: 0.3.3
Summary: Simple extansible editor with projects and outline
Home-page: https://github.com/AnimusPEXUS/wayround_org_pyeditor
Author: Alexey V Gorshkov
Author-email: animus@wayround.org
License: UNKNOWN
Platform: UNKNOWN
Classifier: License :: OSI Approved :: GNU General Public License v3 or later (GPLv3+)
Classifier: Operating System :: POSIX
